{
  "metadata": {
    "configurationVersions": [
      7
    ],
    "clusterVersion": "1.303.42.20241021-231645"
  },
  "id": "ecab63a2-bbe3-4604-9f75-97fedb831dbf",
  "dashboardMetadata": {
    "name": "Redis Enterprise - Active-Active",
    "shared": false,
    "owner": "john.burke@redis.com",
    "popularity": 1,
    "dynamicFilters": {
      "filters": [
        "CUSTOM_DIMENSION:Redis Cluster"
      ],
      "genericTagFilters": []
    },
    "hasConsistentColors": false
  },
  "tiles": [
    {
      "name": "Pending Max Writes",
      "tileType": "DATA_EXPLORER",
      "configured": true,
      "bounds": {
        "top": 266,
        "left": 1292,
        "width": 266,
        "height": 266
      },
      "tileFilter": {},
      "isAutoRefreshDisabled": false,
      "customName": "Single value",
      "queries": [
        {
          "id": "A",
          "metric": "redis.bdb_conns",
          "spaceAggregation": "AUTO",
          "timeAggregation": "DEFAULT",
          "splitBy": [],
          "sortBy": "DESC",
          "sortByDimension": "",
          "filterBy": {
            "nestedFilters": [],
            "criteria": []
          },
          "limit": 20,
          "rate": "NONE",
          "enabled": true
        }
      ],
      "visualConfig": {
        "type": "SINGLE_VALUE",
        "global": {},
        "rules": [
          {
            "matcher": "A:",
            "properties": {
              "color": "DEFAULT"
            },
            "seriesOverrides": []
          }
        ],
        "axes": {
          "xAxis": {
            "visible": true
          },
          "yAxes": []
        },
        "heatmapSettings": {
          "yAxis": "VALUE"
        },
        "singleValueSettings": {
          "showTrend": true,
          "showSparkLine": true,
          "linkTileColorToThreshold": true
        },
        "thresholds": [
          {
            "axisTarget": "LEFT",
            "rules": [
              {
                "color": "#7dc540"
              },
              {
                "color": "#f5d30f"
              },
              {
                "color": "#dc172a"
              }
            ],
            "visible": true
          }
        ],
        "tableSettings": {
          "hiddenColumns": []
        },
        "graphChartSettings": {
          "connectNulls": false
        },
        "honeycombSettings": {
          "showHive": true,
          "showLegend": true,
          "showLabels": false
        }
      },
      "queriesSettings": {
        "resolution": ""
      },
      "metricExpressions": [
        "resolution=Inf&(redis.bdb_conns:splitBy():sort(value(auto,descending)):limit(20)):limit(100):names",
        "resolution=null&(redis.bdb_conns:splitBy():sort(value(auto,descending)):limit(20))"
      ]
    },
    {
      "name": "Ingress - decompressed",
      "tileType": "DATA_EXPLORER",
      "configured": true,
      "bounds": {
        "top": 266,
        "left": 266,
        "width": 494,
        "height": 266
      },
      "tileFilter": {},
      "isAutoRefreshDisabled": false,
      "customName": "Data explorer results",
      "queries": [
        {
          "id": "A",
          "metric": "redis.bdb_crdt_syncer_ingress_bytes_decompressed",
          "spaceAggregation": "AUTO",
          "timeAggregation": "DEFAULT",
          "splitBy": [],
          "sortBy": "DESC",
          "sortByDimension": "",
          "filterBy": {
            "nestedFilters": [],
            "criteria": []
          },
          "limit": 20,
          "rate": "NONE",
          "enabled": true
        },
        {
          "id": "B",
          "metric": "redis.bdb_shard_cpu_user",
          "spaceAggregation": "AUTO",
          "timeAggregation": "DEFAULT",
          "splitBy": [],
          "sortBy": "DESC",
          "sortByDimension": "",
          "filterBy": {
            "nestedFilters": [],
            "criteria": []
          },
          "limit": 20,
          "rate": "NONE",
          "enabled": false
        }
      ],
      "visualConfig": {
        "type": "GRAPH_CHART",
        "global": {},
        "rules": [
          {
            "matcher": "A:",
            "properties": {
              "color": "DEFAULT"
            },
            "seriesOverrides": []
          },
          {
            "matcher": "B:",
            "properties": {
              "color": "DEFAULT"
            },
            "seriesOverrides": []
          }
        ],
        "axes": {
          "xAxis": {
            "displayName": "",
            "visible": true
          },
          "yAxes": [
            {
              "displayName": "",
              "visible": true,
              "min": "AUTO",
              "max": "AUTO",
              "position": "LEFT",
              "queryIds": [
                "A"
              ],
              "defaultAxis": true
            },
            {
              "displayName": "",
              "visible": true,
              "min": "AUTO",
              "max": "AUTO",
              "position": "RIGHT",
              "queryIds": [
                "B"
              ],
              "defaultAxis": true
            }
          ]
        },
        "heatmapSettings": {
          "yAxis": "VALUE",
          "showLabels": false
        },
        "singleValueSettings": {
          "showTrend": true,
          "showSparkLine": true,
          "linkTileColorToThreshold": true
        },
        "thresholds": [
          {
            "axisTarget": "LEFT",
            "rules": [
              {
                "color": "#7dc540"
              },
              {
                "color": "#f5d30f"
              },
              {
                "color": "#dc172a"
              }
            ],
            "visible": true
          }
        ],
        "tableSettings": {
          "hiddenColumns": []
        },
        "graphChartSettings": {
          "connectNulls": false
        },
        "honeycombSettings": {
          "showHive": true,
          "showLegend": true,
          "showLabels": false
        }
      },
      "queriesSettings": {
        "resolution": ""
      },
      "metricExpressions": [
        "resolution=null&(redis.bdb_crdt_syncer_ingress_bytes_decompressed:splitBy():sort(value(auto,descending)):limit(20)):limit(100):names"
      ]
    },
    {
      "name": "Ingress",
      "tileType": "DATA_EXPLORER",
      "configured": true,
      "bounds": {
        "top": 0,
        "left": 266,
        "width": 494,
        "height": 266
      },
      "tileFilter": {},
      "isAutoRefreshDisabled": false,
      "customName": "Data explorer results",
      "queries": [
        {
          "id": "A",
          "metric": "redis.bdb_crdt_syncer_ingress_bytes",
          "spaceAggregation": "AUTO",
          "timeAggregation": "DEFAULT",
          "splitBy": [],
          "sortBy": "DESC",
          "sortByDimension": "",
          "filterBy": {
            "nestedFilters": [],
            "criteria": []
          },
          "limit": 20,
          "rate": "NONE",
          "enabled": true
        },
        {
          "id": "B",
          "metric": "redis.bdb_avg_write_latency",
          "spaceAggregation": "AUTO",
          "timeAggregation": "DEFAULT",
          "splitBy": [],
          "sortBy": "DESC",
          "sortByDimension": "",
          "filterBy": {
            "nestedFilters": [],
            "criteria": []
          },
          "limit": 20,
          "rate": "NONE",
          "enabled": false
        }
      ],
      "visualConfig": {
        "type": "GRAPH_CHART",
        "global": {},
        "rules": [
          {
            "matcher": "A:",
            "properties": {
              "color": "DEFAULT"
            },
            "seriesOverrides": []
          },
          {
            "matcher": "B:",
            "properties": {
              "color": "DEFAULT"
            },
            "seriesOverrides": []
          }
        ],
        "axes": {
          "xAxis": {
            "displayName": "",
            "visible": true
          },
          "yAxes": [
            {
              "displayName": "",
              "visible": true,
              "min": "AUTO",
              "max": "AUTO",
              "position": "LEFT",
              "queryIds": [
                "A"
              ],
              "defaultAxis": true
            },
            {
              "displayName": "",
              "visible": true,
              "min": "AUTO",
              "max": "AUTO",
              "position": "RIGHT",
              "queryIds": [
                "B"
              ],
              "defaultAxis": true
            }
          ]
        },
        "heatmapSettings": {
          "yAxis": "VALUE",
          "showLabels": false
        },
        "singleValueSettings": {
          "showTrend": true,
          "showSparkLine": true,
          "linkTileColorToThreshold": true
        },
        "thresholds": [
          {
            "axisTarget": "LEFT",
            "rules": [
              {
                "color": "#7dc540"
              },
              {
                "color": "#f5d30f"
              },
              {
                "color": "#dc172a"
              }
            ],
            "visible": true
          }
        ],
        "tableSettings": {
          "hiddenColumns": []
        },
        "graphChartSettings": {
          "connectNulls": false
        },
        "honeycombSettings": {
          "showHive": true,
          "showLegend": true,
          "showLabels": false
        }
      },
      "queriesSettings": {
        "resolution": ""
      },
      "metricExpressions": [
        "resolution=null&(redis.bdb_crdt_syncer_ingress_bytes:splitBy():sort(value(auto,descending)):limit(20)):limit(100):names"
      ]
    },
    {
      "name": "Raw DB Size",
      "tileType": "DATA_EXPLORER",
      "configured": true,
      "bounds": {
        "top": 0,
        "left": 1292,
        "width": 266,
        "height": 266
      },
      "tileFilter": {},
      "isAutoRefreshDisabled": false,
      "customName": "Single value",
      "queries": [
        {
          "id": "A",
          "metric": "redis.redis_crdt_raw_dbsize",
          "spaceAggregation": "AUTO",
          "timeAggregation": "DEFAULT",
          "splitBy": [],
          "sortBy": "DESC",
          "sortByDimension": "",
          "filterBy": {
            "nestedFilters": [],
            "criteria": []
          },
          "limit": 20,
          "rate": "NONE",
          "enabled": true
        }
      ],
      "visualConfig": {
        "type": "SINGLE_VALUE",
        "global": {},
        "rules": [
          {
            "matcher": "A:",
            "properties": {
              "color": "DEFAULT"
            },
            "seriesOverrides": []
          }
        ],
        "axes": {
          "xAxis": {
            "visible": true
          },
          "yAxes": []
        },
        "heatmapSettings": {
          "yAxis": "VALUE"
        },
        "singleValueSettings": {
          "showTrend": true,
          "showSparkLine": true,
          "linkTileColorToThreshold": true
        },
        "thresholds": [
          {
            "axisTarget": "LEFT",
            "rules": [
              {
                "color": "#7dc540"
              },
              {
                "color": "#f5d30f"
              },
              {
                "color": "#dc172a"
              }
            ],
            "visible": true
          }
        ],
        "tableSettings": {
          "hiddenColumns": []
        },
        "graphChartSettings": {
          "connectNulls": false
        },
        "honeycombSettings": {
          "showHive": true,
          "showLegend": true,
          "showLabels": false
        }
      },
      "queriesSettings": {
        "resolution": ""
      },
      "metricExpressions": [
        "resolution=Inf&(redis.redis_crdt_raw_dbsize:splitBy():sort(value(auto,descending)):limit(20)):limit(100):names",
        "resolution=null&(redis.redis_crdt_raw_dbsize:splitBy():sort(value(auto,descending)):limit(20))"
      ]
    },
    {
      "name": "Pending Garbage Collection",
      "tileType": "DATA_EXPLORER",
      "configured": true,
      "bounds": {
        "top": 532,
        "left": 1292,
        "width": 266,
        "height": 266
      },
      "tileFilter": {},
      "isAutoRefreshDisabled": false,
      "customName": "Single value",
      "queries": [
        {
          "id": "A",
          "metric": "redis.redis_crdt_gc_pending.count",
          "spaceAggregation": "AUTO",
          "timeAggregation": "DEFAULT",
          "splitBy": [],
          "sortBy": "DESC",
          "sortByDimension": "",
          "filterBy": {
            "nestedFilters": [],
            "criteria": []
          },
          "limit": 20,
          "rate": "NONE",
          "enabled": true
        }
      ],
      "visualConfig": {
        "type": "SINGLE_VALUE",
        "global": {},
        "rules": [
          {
            "matcher": "A:",
            "properties": {
              "color": "DEFAULT"
            },
            "seriesOverrides": []
          }
        ],
        "axes": {
          "xAxis": {
            "visible": true
          },
          "yAxes": []
        },
        "heatmapSettings": {
          "yAxis": "VALUE"
        },
        "singleValueSettings": {
          "showTrend": true,
          "showSparkLine": true,
          "linkTileColorToThreshold": true
        },
        "thresholds": [
          {
            "axisTarget": "LEFT",
            "rules": [
              {
                "color": "#7dc540"
              },
              {
                "color": "#f5d30f"
              },
              {
                "color": "#dc172a"
              }
            ],
            "visible": true
          }
        ],
        "tableSettings": {
          "hiddenColumns": []
        },
        "graphChartSettings": {
          "connectNulls": false
        },
        "honeycombSettings": {
          "showHive": true,
          "showLegend": true,
          "showLabels": false
        }
      },
      "queriesSettings": {
        "resolution": ""
      },
      "metricExpressions": [
        "resolution=Inf&(redis.redis_crdt_gc_pending.count:splitBy():sort(value(auto,descending)):limit(20)):limit(100):names",
        "resolution=null&(redis.redis_crdt_gc_pending.count:splitBy():sort(value(auto,descending)):limit(20))"
      ]
    },
    {
      "name": "Sync Lag",
      "tileType": "DATA_EXPLORER",
      "configured": true,
      "bounds": {
        "top": 266,
        "left": 0,
        "width": 266,
        "height": 266
      },
      "tileFilter": {},
      "isAutoRefreshDisabled": false,
      "customName": "Single value",
      "queries": [
        {
          "id": "A",
          "metric": "redis.bdb_crdt_syncer_local_ingress_lag_time",
          "spaceAggregation": "AUTO",
          "timeAggregation": "DEFAULT",
          "splitBy": [],
          "sortBy": "DESC",
          "sortByDimension": "",
          "filterBy": {
            "nestedFilters": [],
            "criteria": []
          },
          "limit": 20,
          "rate": "NONE",
          "enabled": true
        }
      ],
      "visualConfig": {
        "type": "SINGLE_VALUE",
        "global": {},
        "rules": [
          {
            "matcher": "A:",
            "properties": {
              "color": "DEFAULT"
            },
            "seriesOverrides": []
          }
        ],
        "axes": {
          "xAxis": {
            "visible": true
          },
          "yAxes": []
        },
        "heatmapSettings": {
          "yAxis": "VALUE"
        },
        "singleValueSettings": {
          "showTrend": true,
          "showSparkLine": true,
          "linkTileColorToThreshold": true
        },
        "thresholds": [
          {
            "axisTarget": "LEFT",
            "rules": [
              {
                "color": "#7dc540"
              },
              {
                "color": "#f5d30f"
              },
              {
                "color": "#dc172a"
              }
            ],
            "visible": true
          }
        ],
        "tableSettings": {
          "hiddenColumns": []
        },
        "graphChartSettings": {
          "connectNulls": false
        },
        "honeycombSettings": {
          "showHive": true,
          "showLegend": true,
          "showLabels": false
        }
      },
      "queriesSettings": {
        "resolution": ""
      },
      "metricExpressions": [
        "resolution=Inf&(redis.bdb_crdt_syncer_local_ingress_lag_time:splitBy():sort(value(auto,descending)):limit(20)):limit(100):names",
        "resolution=null&(redis.bdb_crdt_syncer_local_ingress_lag_time:splitBy():sort(value(auto,descending)):limit(20))"
      ]
    },
    {
      "name": "Sync Backlog",
      "tileType": "DATA_EXPLORER",
      "configured": true,
      "bounds": {
        "top": 532,
        "left": 0,
        "width": 266,
        "height": 266
      },
      "tileFilter": {},
      "isAutoRefreshDisabled": false,
      "customName": "Single value",
      "queries": [
        {
          "id": "A",
          "spaceAggregation": "AUTO",
          "timeAggregation": "DEFAULT",
          "splitBy": [],
          "metricSelector": "redis.redis_crdt_backlog_size.count",
          "rate": "NONE",
          "enabled": true
        }
      ],
      "visualConfig": {
        "type": "SINGLE_VALUE",
        "global": {},
        "rules": [
          {
            "matcher": "A:",
            "properties": {
              "color": "DEFAULT"
            },
            "seriesOverrides": []
          }
        ],
        "axes": {
          "xAxis": {
            "visible": true
          },
          "yAxes": []
        },
        "heatmapSettings": {
          "yAxis": "VALUE"
        },
        "singleValueSettings": {
          "showTrend": true,
          "showSparkLine": true,
          "linkTileColorToThreshold": true
        },
        "thresholds": [
          {
            "axisTarget": "LEFT",
            "rules": [
              {
                "color": "#7dc540"
              },
              {
                "color": "#f5d30f"
              },
              {
                "color": "#dc172a"
              }
            ],
            "visible": true
          }
        ],
        "tableSettings": {
          "hiddenColumns": []
        },
        "graphChartSettings": {
          "connectNulls": false
        },
        "honeycombSettings": {
          "showHive": true,
          "showLegend": true,
          "showLabels": false
        }
      },
      "queriesSettings": {
        "resolution": ""
      },
      "metricExpressions": [
        "resolution=Inf&(redis.redis_crdt_backlog_size.count):limit(100):names",
        "resolution=null&(redis.redis_crdt_backlog_size.count)"
      ]
    },
    {
      "name": "Ingestion Sync Lag",
      "tileType": "DATA_EXPLORER",
      "configured": true,
      "bounds": {
        "top": 532,
        "left": 266,
        "width": 494,
        "height": 266
      },
      "tileFilter": {},
      "isAutoRefreshDisabled": false,
      "customName": "Data explorer results",
      "queries": [
        {
          "id": "A",
          "metric": "redis.bdb_crdt_syncer_local_ingress_lag_time",
          "spaceAggregation": "AUTO",
          "timeAggregation": "DEFAULT",
          "splitBy": [],
          "sortBy": "DESC",
          "sortByDimension": "",
          "filterBy": {
            "nestedFilters": [],
            "criteria": []
          },
          "limit": 20,
          "rate": "NONE",
          "enabled": true
        }
      ],
      "visualConfig": {
        "type": "GRAPH_CHART",
        "global": {},
        "rules": [
          {
            "matcher": "A:",
            "properties": {
              "color": "DEFAULT"
            },
            "seriesOverrides": []
          }
        ],
        "axes": {
          "xAxis": {
            "displayName": "",
            "visible": true
          },
          "yAxes": [
            {
              "displayName": "",
              "visible": true,
              "min": "AUTO",
              "max": "AUTO",
              "position": "LEFT",
              "queryIds": [
                "A"
              ],
              "defaultAxis": true
            }
          ]
        },
        "heatmapSettings": {
          "yAxis": "VALUE",
          "showLabels": false
        },
        "singleValueSettings": {
          "showTrend": true,
          "showSparkLine": true,
          "linkTileColorToThreshold": true
        },
        "thresholds": [
          {
            "axisTarget": "LEFT",
            "rules": [
              {
                "color": "#7dc540"
              },
              {
                "color": "#f5d30f"
              },
              {
                "color": "#dc172a"
              }
            ],
            "visible": true
          }
        ],
        "tableSettings": {
          "hiddenColumns": []
        },
        "graphChartSettings": {
          "connectNulls": false
        },
        "honeycombSettings": {
          "showHive": true,
          "showLegend": true,
          "showLabels": false
        }
      },
      "queriesSettings": {
        "resolution": ""
      },
      "metricExpressions": [
        "resolution=null&(redis.bdb_crdt_syncer_local_ingress_lag_time:splitBy():sort(value(auto,descending)):limit(20)):limit(100):names"
      ]
    },
    {
      "name": "Egress - decompressed",
      "tileType": "DATA_EXPLORER",
      "configured": true,
      "bounds": {
        "top": 266,
        "left": 760,
        "width": 532,
        "height": 266
      },
      "tileFilter": {},
      "isAutoRefreshDisabled": false,
      "customName": "Data explorer results",
      "queries": [
        {
          "id": "A",
          "metric": "redis.bdb_crdt_syncer_egress_bytes_decompressed",
          "spaceAggregation": "AUTO",
          "timeAggregation": "DEFAULT",
          "splitBy": [],
          "sortBy": "DESC",
          "sortByDimension": "",
          "filterBy": {
            "nestedFilters": [],
            "criteria": []
          },
          "limit": 20,
          "rate": "NONE",
          "enabled": true
        }
      ],
      "visualConfig": {
        "type": "GRAPH_CHART",
        "global": {},
        "rules": [
          {
            "matcher": "A:",
            "properties": {
              "color": "DEFAULT"
            },
            "seriesOverrides": []
          }
        ],
        "axes": {
          "xAxis": {
            "displayName": "",
            "visible": true
          },
          "yAxes": [
            {
              "displayName": "",
              "visible": true,
              "min": "AUTO",
              "max": "AUTO",
              "position": "LEFT",
              "queryIds": [
                "A"
              ],
              "defaultAxis": true
            }
          ]
        },
        "heatmapSettings": {
          "yAxis": "VALUE",
          "showLabels": false
        },
        "singleValueSettings": {
          "showTrend": true,
          "showSparkLine": true,
          "linkTileColorToThreshold": true
        },
        "thresholds": [
          {
            "axisTarget": "LEFT",
            "rules": [
              {
                "color": "#7dc540"
              },
              {
                "color": "#f5d30f"
              },
              {
                "color": "#dc172a"
              }
            ],
            "visible": true
          }
        ],
        "tableSettings": {
          "hiddenColumns": []
        },
        "graphChartSettings": {
          "connectNulls": false
        },
        "honeycombSettings": {
          "showHive": true,
          "showLegend": true,
          "showLabels": false
        }
      },
      "queriesSettings": {
        "resolution": ""
      },
      "metricExpressions": [
        "resolution=null&(redis.bdb_crdt_syncer_egress_bytes_decompressed:splitBy():sort(value(auto,descending)):limit(20)):limit(100):names"
      ]
    },
    {
      "name": "Egress",
      "tileType": "DATA_EXPLORER",
      "configured": true,
      "bounds": {
        "top": 0,
        "left": 760,
        "width": 532,
        "height": 266
      },
      "tileFilter": {},
      "isAutoRefreshDisabled": false,
      "customName": "Data explorer results",
      "queries": [
        {
          "id": "C",
          "metric": "redis.bdb_crdt_syncer_egress_bytes",
          "spaceAggregation": "AUTO",
          "timeAggregation": "DEFAULT",
          "splitBy": [],
          "sortBy": "DESC",
          "sortByDimension": "",
          "filterBy": {
            "nestedFilters": [],
            "criteria": []
          },
          "limit": 20,
          "rate": "NONE",
          "enabled": true
        }
      ],
      "visualConfig": {
        "type": "GRAPH_CHART",
        "global": {},
        "rules": [
          {
            "matcher": "C:",
            "properties": {
              "color": "DEFAULT"
            },
            "seriesOverrides": []
          }
        ],
        "axes": {
          "xAxis": {
            "displayName": "",
            "visible": true
          },
          "yAxes": [
            {
              "displayName": "",
              "visible": true,
              "min": "AUTO",
              "max": "AUTO",
              "position": "LEFT",
              "queryIds": [
                "C"
              ],
              "defaultAxis": true
            }
          ]
        },
        "heatmapSettings": {
          "yAxis": "VALUE",
          "showLabels": false
        },
        "singleValueSettings": {
          "showTrend": true,
          "showSparkLine": true,
          "linkTileColorToThreshold": true
        },
        "thresholds": [
          {
            "axisTarget": "LEFT",
            "rules": [
              {
                "color": "#7dc540"
              },
              {
                "color": "#f5d30f"
              },
              {
                "color": "#dc172a"
              }
            ],
            "visible": true
          }
        ],
        "tableSettings": {
          "hiddenColumns": []
        },
        "graphChartSettings": {
          "connectNulls": false
        },
        "honeycombSettings": {
          "showHive": true,
          "showLegend": true,
          "showLabels": false
        }
      },
      "queriesSettings": {
        "resolution": ""
      },
      "metricExpressions": [
        "resolution=null&(redis.bdb_crdt_syncer_egress_bytes:splitBy():sort(value(auto,descending)):limit(20)):limit(100):names"
      ]
    },
    {
      "name": "Merge Requests",
      "tileType": "DATA_EXPLORER",
      "configured": true,
      "bounds": {
        "top": 532,
        "left": 760,
        "width": 532,
        "height": 266
      },
      "tileFilter": {},
      "isAutoRefreshDisabled": false,
      "customName": "Data explorer results",
      "queries": [
        {
          "id": "A",
          "metric": "redis.redis_crdt_merge_reqs.count",
          "spaceAggregation": "AUTO",
          "timeAggregation": "DEFAULT",
          "splitBy": [],
          "sortBy": "DESC",
          "sortByDimension": "",
          "filterBy": {
            "nestedFilters": [],
            "criteria": []
          },
          "limit": 20,
          "rate": "NONE",
          "enabled": true
        }
      ],
      "visualConfig": {
        "type": "GRAPH_CHART",
        "global": {},
        "rules": [
          {
            "matcher": "A:",
            "properties": {
              "color": "DEFAULT"
            },
            "seriesOverrides": []
          }
        ],
        "axes": {
          "xAxis": {
            "displayName": "",
            "visible": true
          },
          "yAxes": [
            {
              "displayName": "",
              "visible": true,
              "min": "AUTO",
              "max": "AUTO",
              "position": "LEFT",
              "queryIds": [
                "A"
              ],
              "defaultAxis": true
            }
          ]
        },
        "heatmapSettings": {
          "yAxis": "VALUE",
          "showLabels": false
        },
        "singleValueSettings": {
          "showTrend": true,
          "showSparkLine": true,
          "linkTileColorToThreshold": true
        },
        "thresholds": [
          {
            "axisTarget": "LEFT",
            "rules": [
              {
                "color": "#7dc540"
              },
              {
                "color": "#f5d30f"
              },
              {
                "color": "#dc172a"
              }
            ],
            "visible": true
          }
        ],
        "tableSettings": {
          "hiddenColumns": []
        },
        "graphChartSettings": {
          "connectNulls": false
        },
        "honeycombSettings": {
          "showHive": true,
          "showLegend": true,
          "showLabels": false
        }
      },
      "queriesSettings": {
        "resolution": ""
      },
      "metricExpressions": [
        "resolution=null&(redis.redis_crdt_merge_reqs.count:splitBy():sort(value(auto,descending)):limit(20)):limit(100):names"
      ]
    },
    {
      "name": "Sync Status",
      "tileType": "DATA_EXPLORER",
      "configured": true,
      "bounds": {
        "top": 0,
        "left": 0,
        "width": 266,
        "height": 266
      },
      "tileFilter": {},
      "isAutoRefreshDisabled": false,
      "customName": "Single value",
      "queries": [
        {
          "id": "A",
          "metric": "redis.bdb_crdt_syncer_status",
          "spaceAggregation": "AUTO",
          "timeAggregation": "DEFAULT",
          "splitBy": [],
          "sortBy": "DESC",
          "sortByDimension": "",
          "filterBy": {
            "nestedFilters": [],
            "criteria": []
          },
          "limit": 20,
          "rate": "NONE",
          "enabled": true
        }
      ],
      "visualConfig": {
        "type": "SINGLE_VALUE",
        "global": {},
        "rules": [
          {
            "matcher": "A:",
            "properties": {
              "color": "DEFAULT"
            },
            "seriesOverrides": []
          }
        ],
        "axes": {
          "xAxis": {
            "visible": true
          },
          "yAxes": []
        },
        "heatmapSettings": {
          "yAxis": "VALUE"
        },
        "singleValueSettings": {
          "showTrend": true,
          "showSparkLine": true,
          "linkTileColorToThreshold": true
        },
        "thresholds": [
          {
            "axisTarget": "LEFT",
            "rules": [
              {
                "value": 0,
                "color": "#7dc540"
              },
              {
                "value": 1,
                "color": "#f5d30f"
              },
              {
                "value": 2,
                "color": "#dc172a"
              }
            ],
            "queryId": "",
            "visible": true
          }
        ],
        "tableSettings": {
          "hiddenColumns": []
        },
        "graphChartSettings": {
          "connectNulls": false
        },
        "honeycombSettings": {
          "showHive": true,
          "showLegend": true,
          "showLabels": false
        }
      },
      "queriesSettings": {
        "resolution": ""
      },
      "metricExpressions": [
        "resolution=Inf&(redis.bdb_crdt_syncer_status:splitBy():sort(value(auto,descending)):limit(20)):limit(100):names",
        "resolution=null&(redis.bdb_crdt_syncer_status:splitBy():sort(value(auto,descending)):limit(20))"
      ]
    }
  ]
}
