{
  "metadata": {
    "configurationVersions": [
      7
    ],
    "clusterVersion": "1.302.53.20241017-021333"
  },
  "id": "614c8839-e3a7-48c1-bcab-d0c0721f8725",
  "dashboardMetadata": {
    "name": "Redis Enterprise - Shard",
    "shared": false,
    "owner": "john.burke@redis.com",
    "tags": [
      "cluster"
    ],
    "popularity": 1,
    "dynamicFilters": {
      "filters": [
        "CUSTOM_DIMENSION:Redis Shard",
        "CUSTOM_DIMENSION:Redis Cluster",
        "CUSTOM_DIMENSION:Redis Database",
        "CUSTOM_DIMENSION:Redis Node"
      ],
      "genericTagFilters": []
    },
    "hasConsistentColors": false
  },
  "tiles": [
    {
      "name": "Shard Rss Fragmentation",
      "tileType": "DATA_EXPLORER",
      "configured": true,
      "bounds": {
        "top": 1368,
        "left": 418,
        "width": 380,
        "height": 228
      },
      "tileFilter": {},
      "isAutoRefreshDisabled": false,
      "customName": "Single value",
      "queries": [
        {
          "id": "A",
          "metric": "redis.bdb_conns",
          "spaceAggregation": "AUTO",
          "timeAggregation": "DEFAULT",
          "splitBy": [],
          "sortBy": "DESC",
          "sortByDimension": "",
          "filterBy": {
            "nestedFilters": [],
            "criteria": []
          },
          "limit": 20,
          "rate": "NONE",
          "enabled": true
        }
      ],
      "visualConfig": {
        "type": "SINGLE_VALUE",
        "global": {},
        "rules": [
          {
            "matcher": "A:",
            "properties": {
              "color": "DEFAULT"
            },
            "seriesOverrides": []
          }
        ],
        "axes": {
          "xAxis": {
            "visible": true
          },
          "yAxes": []
        },
        "heatmapSettings": {
          "yAxis": "VALUE"
        },
        "singleValueSettings": {
          "showTrend": true,
          "showSparkLine": true,
          "linkTileColorToThreshold": true
        },
        "thresholds": [
          {
            "axisTarget": "LEFT",
            "rules": [
              {
                "color": "#7dc540"
              },
              {
                "color": "#f5d30f"
              },
              {
                "color": "#dc172a"
              }
            ],
            "visible": true
          }
        ],
        "tableSettings": {
          "hiddenColumns": []
        },
        "graphChartSettings": {
          "connectNulls": false
        },
        "honeycombSettings": {
          "showHive": true,
          "showLegend": true,
          "showLabels": false
        }
      },
      "queriesSettings": {
        "resolution": ""
      },
      "metricExpressions": [
        "resolution=Inf&(redis.bdb_conns:splitBy():sort(value(auto,descending)):limit(20)):limit(100):names",
        "resolution=null&(redis.bdb_conns:splitBy():sort(value(auto,descending)):limit(20))"
      ]
    },
    {
      "name": "Memory",
      "tileType": "DATA_EXPLORER",
      "configured": true,
      "bounds": {
        "top": 38,
        "left": 532,
        "width": 266,
        "height": 228
      },
      "tileFilter": {},
      "isAutoRefreshDisabled": false,
      "customName": "Single value",
      "queries": [
        {
          "id": "A",
          "metric": "redis.bdb_total_req",
          "spaceAggregation": "AUTO",
          "timeAggregation": "DEFAULT",
          "splitBy": [],
          "sortBy": "DESC",
          "sortByDimension": "",
          "filterBy": {
            "nestedFilters": [],
            "criteria": []
          },
          "limit": 20,
          "rate": "NONE",
          "enabled": true
        }
      ],
      "visualConfig": {
        "type": "SINGLE_VALUE",
        "global": {},
        "rules": [
          {
            "matcher": "A:",
            "properties": {
              "color": "DEFAULT"
            },
            "seriesOverrides": []
          }
        ],
        "axes": {
          "xAxis": {
            "visible": true
          },
          "yAxes": []
        },
        "heatmapSettings": {
          "yAxis": "VALUE"
        },
        "singleValueSettings": {
          "showTrend": true,
          "showSparkLine": true,
          "linkTileColorToThreshold": true
        },
        "thresholds": [
          {
            "axisTarget": "LEFT",
            "rules": [
              {
                "color": "#7dc540"
              },
              {
                "color": "#f5d30f"
              },
              {
                "color": "#dc172a"
              }
            ],
            "visible": true
          }
        ],
        "tableSettings": {
          "hiddenColumns": []
        },
        "graphChartSettings": {
          "connectNulls": false
        },
        "honeycombSettings": {
          "showHive": true,
          "showLegend": true,
          "showLabels": false
        }
      },
      "queriesSettings": {
        "resolution": ""
      },
      "metricExpressions": [
        "resolution=Inf&(redis.bdb_total_req:splitBy():sort(value(auto,descending)):limit(20)):limit(100):names",
        "resolution=null&(redis.bdb_total_req:splitBy():sort(value(auto,descending)):limit(20))"
      ]
    },
    {
      "name": "Latency",
      "tileType": "DATA_EXPLORER",
      "configured": true,
      "bounds": {
        "top": 836,
        "left": 0,
        "width": 532,
        "height": 228
      },
      "tileFilter": {},
      "isAutoRefreshDisabled": false,
      "customName": "Data explorer results",
      "queries": [
        {
          "id": "A",
          "metric": "redis.bdb_avg_read_latency",
          "spaceAggregation": "AUTO",
          "timeAggregation": "DEFAULT",
          "splitBy": [],
          "sortBy": "DESC",
          "sortByDimension": "",
          "filterBy": {
            "nestedFilters": [],
            "criteria": []
          },
          "limit": 20,
          "rate": "NONE",
          "enabled": true
        },
        {
          "id": "B",
          "metric": "redis.bdb_avg_write_latency",
          "spaceAggregation": "AUTO",
          "timeAggregation": "DEFAULT",
          "splitBy": [],
          "sortBy": "DESC",
          "sortByDimension": "",
          "filterBy": {
            "nestedFilters": [],
            "criteria": []
          },
          "limit": 20,
          "rate": "NONE",
          "enabled": true
        }
      ],
      "visualConfig": {
        "type": "GRAPH_CHART",
        "global": {},
        "rules": [
          {
            "matcher": "A:",
            "properties": {
              "color": "DEFAULT"
            },
            "seriesOverrides": []
          },
          {
            "matcher": "B:",
            "properties": {
              "color": "DEFAULT"
            },
            "seriesOverrides": []
          }
        ],
        "axes": {
          "xAxis": {
            "displayName": "",
            "visible": true
          },
          "yAxes": [
            {
              "displayName": "",
              "visible": true,
              "min": "AUTO",
              "max": "AUTO",
              "position": "LEFT",
              "queryIds": [
                "A",
                "B"
              ],
              "defaultAxis": true
            }
          ]
        },
        "heatmapSettings": {
          "yAxis": "VALUE",
          "showLabels": false
        },
        "singleValueSettings": {
          "showTrend": true,
          "showSparkLine": true,
          "linkTileColorToThreshold": true
        },
        "thresholds": [
          {
            "axisTarget": "LEFT",
            "rules": [
              {
                "color": "#7dc540"
              },
              {
                "color": "#f5d30f"
              },
              {
                "color": "#dc172a"
              }
            ],
            "visible": true
          }
        ],
        "tableSettings": {
          "hiddenColumns": []
        },
        "graphChartSettings": {
          "connectNulls": false
        },
        "honeycombSettings": {
          "showHive": true,
          "showLegend": true,
          "showLabels": false
        }
      },
      "queriesSettings": {
        "resolution": ""
      },
      "metricExpressions": [
        "resolution=null&(redis.bdb_avg_read_latency:splitBy():sort(value(auto,descending)):limit(20)):limit(100):names,(redis.bdb_avg_write_latency:splitBy():sort(value(auto,descending)):limit(20)):limit(100):names"
      ]
    },
    {
      "name": "Total Fragmentation",
      "tileType": "DATA_EXPLORER",
      "configured": true,
      "bounds": {
        "top": 1368,
        "left": 0,
        "width": 418,
        "height": 228
      },
      "tileFilter": {},
      "isAutoRefreshDisabled": false,
      "customName": "Data explorer results",
      "queries": [
        {
          "id": "A",
          "metric": "redis.bdb_read_misses",
          "spaceAggregation": "AUTO",
          "timeAggregation": "DEFAULT",
          "splitBy": [],
          "sortBy": "DESC",
          "sortByDimension": "",
          "filterBy": {
            "nestedFilters": [],
            "criteria": []
          },
          "limit": 20,
          "rate": "NONE",
          "enabled": true
        },
        {
          "id": "B",
          "metric": "redis.bdb_write_misses",
          "spaceAggregation": "AUTO",
          "timeAggregation": "DEFAULT",
          "splitBy": [],
          "sortBy": "DESC",
          "sortByDimension": "",
          "filterBy": {
            "nestedFilters": [],
            "criteria": []
          },
          "limit": 20,
          "rate": "NONE",
          "enabled": true
        }
      ],
      "visualConfig": {
        "type": "GRAPH_CHART",
        "global": {},
        "rules": [
          {
            "matcher": "A:",
            "properties": {
              "color": "DEFAULT"
            },
            "seriesOverrides": []
          },
          {
            "matcher": "B:",
            "properties": {
              "color": "DEFAULT"
            },
            "seriesOverrides": []
          }
        ],
        "axes": {
          "xAxis": {
            "displayName": "",
            "visible": true
          },
          "yAxes": [
            {
              "displayName": "",
              "visible": true,
              "min": "AUTO",
              "max": "AUTO",
              "position": "LEFT",
              "queryIds": [
                "A"
              ],
              "defaultAxis": true
            },
            {
              "displayName": "",
              "visible": true,
              "min": "AUTO",
              "max": "AUTO",
              "position": "RIGHT",
              "queryIds": [
                "B"
              ],
              "defaultAxis": true
            }
          ]
        },
        "heatmapSettings": {
          "yAxis": "VALUE",
          "showLabels": false
        },
        "singleValueSettings": {
          "showTrend": true,
          "showSparkLine": true,
          "linkTileColorToThreshold": true
        },
        "thresholds": [
          {
            "axisTarget": "LEFT",
            "rules": [
              {
                "color": "#7dc540"
              },
              {
                "color": "#f5d30f"
              },
              {
                "color": "#dc172a"
              }
            ],
            "visible": true
          }
        ],
        "tableSettings": {
          "hiddenColumns": []
        },
        "graphChartSettings": {
          "connectNulls": false
        },
        "honeycombSettings": {
          "showHive": true,
          "showLegend": true,
          "showLabels": false
        }
      },
      "queriesSettings": {
        "resolution": ""
      },
      "metricExpressions": [
        "resolution=null&(redis.bdb_read_misses:splitBy():sort(value(auto,descending)):limit(20)):limit(100):names,(redis.bdb_write_misses:splitBy():sort(value(auto,descending)):limit(20)):limit(100):names"
      ]
    },
    {
      "name": "CPU Usage",
      "tileType": "DATA_EXPLORER",
      "configured": true,
      "bounds": {
        "top": 38,
        "left": 266,
        "width": 266,
        "height": 228
      },
      "tileFilter": {},
      "isAutoRefreshDisabled": false,
      "customName": "Single value",
      "queries": [
        {
          "id": "A",
          "metric": "redis.redis_process_cpu_usage_percent",
          "spaceAggregation": "AUTO",
          "timeAggregation": "DEFAULT",
          "splitBy": [],
          "sortBy": "DESC",
          "sortByDimension": "",
          "filterBy": {
            "nestedFilters": [],
            "criteria": []
          },
          "limit": 20,
          "rate": "NONE",
          "enabled": true
        }
      ],
      "visualConfig": {
        "type": "SINGLE_VALUE",
        "global": {},
        "rules": [
          {
            "matcher": "A:",
            "properties": {
              "color": "DEFAULT"
            },
            "seriesOverrides": []
          }
        ],
        "axes": {
          "xAxis": {
            "visible": true
          },
          "yAxes": []
        },
        "heatmapSettings": {
          "yAxis": "VALUE"
        },
        "singleValueSettings": {
          "showTrend": true,
          "showSparkLine": true,
          "linkTileColorToThreshold": true
        },
        "thresholds": [
          {
            "axisTarget": "LEFT",
            "rules": [
              {
                "color": "#7dc540"
              },
              {
                "color": "#f5d30f"
              },
              {
                "color": "#dc172a"
              }
            ],
            "visible": true
          }
        ],
        "tableSettings": {
          "hiddenColumns": []
        },
        "graphChartSettings": {
          "connectNulls": false
        },
        "honeycombSettings": {
          "showHive": true,
          "showLegend": true,
          "showLabels": false
        }
      },
      "queriesSettings": {
        "resolution": ""
      },
      "metricExpressions": [
        "resolution=Inf&(redis.redis_process_cpu_usage_percent:splitBy():sort(value(auto,descending)):limit(20)):limit(100):names",
        "resolution=null&(redis.redis_process_cpu_usage_percent:splitBy():sort(value(auto,descending)):limit(20))"
      ]
    },
    {
      "name": "Summary",
      "tileType": "HEADER",
      "configured": true,
      "bounds": {
        "top": 0,
        "left": 0,
        "width": 1596,
        "height": 38
      },
      "tileFilter": {},
      "isAutoRefreshDisabled": false
    },
    {
      "name": "Connections",
      "tileType": "DATA_EXPLORER",
      "configured": true,
      "bounds": {
        "top": 38,
        "left": 1064,
        "width": 266,
        "height": 228
      },
      "tileFilter": {},
      "isAutoRefreshDisabled": false,
      "customName": "Single value",
      "queries": [
        {
          "id": "A",
          "metric": "redis.bdb_conns",
          "spaceAggregation": "AUTO",
          "timeAggregation": "DEFAULT",
          "splitBy": [],
          "sortBy": "DESC",
          "sortByDimension": "",
          "filterBy": {
            "nestedFilters": [],
            "criteria": []
          },
          "limit": 20,
          "rate": "NONE",
          "enabled": true
        }
      ],
      "visualConfig": {
        "type": "SINGLE_VALUE",
        "global": {},
        "rules": [
          {
            "matcher": "A:",
            "properties": {
              "color": "DEFAULT"
            },
            "seriesOverrides": []
          }
        ],
        "axes": {
          "xAxis": {
            "visible": true
          },
          "yAxes": []
        },
        "heatmapSettings": {
          "yAxis": "VALUE"
        },
        "singleValueSettings": {
          "showTrend": true,
          "showSparkLine": true,
          "linkTileColorToThreshold": true
        },
        "thresholds": [
          {
            "axisTarget": "LEFT",
            "rules": [
              {
                "color": "#7dc540"
              },
              {
                "color": "#f5d30f"
              },
              {
                "color": "#dc172a"
              }
            ],
            "visible": true
          }
        ],
        "tableSettings": {
          "hiddenColumns": []
        },
        "graphChartSettings": {
          "connectNulls": false
        },
        "honeycombSettings": {
          "showHive": true,
          "showLegend": true,
          "showLabels": false
        }
      },
      "queriesSettings": {
        "resolution": ""
      },
      "metricExpressions": [
        "resolution=Inf&(redis.bdb_conns:splitBy():sort(value(auto,descending)):limit(20)):limit(100):names",
        "resolution=null&(redis.bdb_conns:splitBy():sort(value(auto,descending)):limit(20))"
      ]
    },
    {
      "name": "Key Count",
      "tileType": "DATA_EXPLORER",
      "configured": true,
      "bounds": {
        "top": 38,
        "left": 798,
        "width": 266,
        "height": 228
      },
      "tileFilter": {},
      "isAutoRefreshDisabled": false,
      "customName": "Single value",
      "queries": [
        {
          "id": "A",
          "metric": "redis.redis_db0_keys",
          "spaceAggregation": "AUTO",
          "timeAggregation": "DEFAULT",
          "splitBy": [],
          "sortBy": "DESC",
          "sortByDimension": "",
          "filterBy": {
            "nestedFilters": [],
            "criteria": []
          },
          "limit": 20,
          "rate": "NONE",
          "enabled": true
        }
      ],
      "visualConfig": {
        "type": "SINGLE_VALUE",
        "global": {},
        "rules": [
          {
            "matcher": "A:",
            "properties": {
              "color": "DEFAULT"
            },
            "seriesOverrides": []
          }
        ],
        "axes": {
          "xAxis": {
            "visible": true
          },
          "yAxes": []
        },
        "heatmapSettings": {
          "yAxis": "VALUE"
        },
        "singleValueSettings": {
          "showTrend": true,
          "showSparkLine": true,
          "linkTileColorToThreshold": true
        },
        "thresholds": [
          {
            "axisTarget": "LEFT",
            "rules": [
              {
                "color": "#7dc540"
              },
              {
                "color": "#f5d30f"
              },
              {
                "color": "#dc172a"
              }
            ],
            "visible": true
          }
        ],
        "tableSettings": {
          "hiddenColumns": []
        },
        "graphChartSettings": {
          "connectNulls": false
        },
        "honeycombSettings": {
          "showHive": true,
          "showLegend": true,
          "showLabels": false
        }
      },
      "queriesSettings": {
        "resolution": ""
      },
      "metricExpressions": [
        "resolution=Inf&(redis.redis_db0_keys:splitBy():sort(value(auto,descending)):limit(20)):limit(100):names",
        "resolution=null&(redis.redis_db0_keys:splitBy():sort(value(auto,descending)):limit(20))"
      ]
    },
    {
      "name": "Forwarding",
      "tileType": "DATA_EXPLORER",
      "configured": true,
      "bounds": {
        "top": 38,
        "left": 1330,
        "width": 266,
        "height": 228
      },
      "tileFilter": {},
      "isAutoRefreshDisabled": false,
      "customName": "Single value",
      "queries": [
        {
          "id": "A",
          "metric": "redis.redis_forwarding_state",
          "spaceAggregation": "AUTO",
          "timeAggregation": "DEFAULT",
          "splitBy": [],
          "sortBy": "DESC",
          "sortByDimension": "",
          "filterBy": {
            "nestedFilters": [],
            "criteria": []
          },
          "limit": 20,
          "rate": "NONE",
          "enabled": true
        }
      ],
      "visualConfig": {
        "type": "SINGLE_VALUE",
        "global": {},
        "rules": [
          {
            "matcher": "A:",
            "properties": {
              "color": "DEFAULT"
            },
            "seriesOverrides": []
          }
        ],
        "axes": {
          "xAxis": {
            "visible": true
          },
          "yAxes": []
        },
        "heatmapSettings": {
          "yAxis": "VALUE"
        },
        "singleValueSettings": {
          "showTrend": true,
          "showSparkLine": true,
          "linkTileColorToThreshold": true
        },
        "thresholds": [
          {
            "axisTarget": "LEFT",
            "rules": [
              {
                "color": "#7dc540"
              },
              {
                "color": "#f5d30f"
              },
              {
                "color": "#dc172a"
              }
            ],
            "visible": true
          }
        ],
        "tableSettings": {
          "hiddenColumns": []
        },
        "graphChartSettings": {
          "connectNulls": false
        },
        "honeycombSettings": {
          "showHive": true,
          "showLegend": true,
          "showLabels": false
        }
      },
      "queriesSettings": {
        "resolution": ""
      },
      "metricExpressions": [
        "resolution=Inf&(redis.redis_forwarding_state:splitBy():sort(value(auto,descending)):limit(20)):limit(100):names",
        "resolution=null&(redis.redis_forwarding_state:splitBy():sort(value(auto,descending)):limit(20))"
      ]
    },
    {
      "name": "Memory",
      "tileType": "HEADER",
      "configured": true,
      "bounds": {
        "top": 266,
        "left": 0,
        "width": 1596,
        "height": 38
      },
      "tileFilter": {},
      "isAutoRefreshDisabled": false
    },
    {
      "name": "CPU",
      "tileType": "HEADER",
      "configured": true,
      "bounds": {
        "top": 532,
        "left": 0,
        "width": 1596,
        "height": 38
      },
      "tileFilter": {},
      "isAutoRefreshDisabled": false
    },
    {
      "name": "Network",
      "tileType": "HEADER",
      "configured": true,
      "bounds": {
        "top": 798,
        "left": 0,
        "width": 1596,
        "height": 38
      },
      "tileFilter": {},
      "isAutoRefreshDisabled": false
    },
    {
      "name": "Keys",
      "tileType": "HEADER",
      "configured": true,
      "bounds": {
        "top": 1064,
        "left": 0,
        "width": 1596,
        "height": 38
      },
      "tileFilter": {},
      "isAutoRefreshDisabled": false
    },
    {
      "name": "Cache",
      "tileType": "HEADER",
      "configured": true,
      "bounds": {
        "top": 1330,
        "left": 0,
        "width": 1596,
        "height": 38
      },
      "tileFilter": {},
      "isAutoRefreshDisabled": false
    },
    {
      "name": "Allocated Memory",
      "tileType": "DATA_EXPLORER",
      "configured": true,
      "bounds": {
        "top": 304,
        "left": 0,
        "width": 380,
        "height": 228
      },
      "tileFilter": {},
      "isAutoRefreshDisabled": false,
      "customName": "Single value",
      "queries": [
        {
          "id": "A",
          "spaceAggregation": "AUTO",
          "timeAggregation": "DEFAULT",
          "splitBy": [],
          "metricSelector": "(redis.redis_allocator_allocated:splitBy():sort(value(auto,descending)):limit(20)/redis.bdb_memory_limit:splitBy():sort(value(auto,descending)):limit(20))*100",
          "rate": "NONE",
          "enabled": true
        }
      ],
      "visualConfig": {
        "type": "SINGLE_VALUE",
        "global": {},
        "rules": [
          {
            "matcher": "A:",
            "properties": {
              "color": "DEFAULT"
            },
            "seriesOverrides": []
          }
        ],
        "axes": {
          "xAxis": {
            "visible": true
          },
          "yAxes": []
        },
        "heatmapSettings": {
          "yAxis": "VALUE"
        },
        "singleValueSettings": {
          "showTrend": true,
          "showSparkLine": true,
          "linkTileColorToThreshold": true
        },
        "thresholds": [
          {
            "axisTarget": "LEFT",
            "rules": [
              {
                "color": "#7dc540"
              },
              {
                "color": "#f5d30f"
              },
              {
                "color": "#dc172a"
              }
            ],
            "visible": true
          }
        ],
        "tableSettings": {
          "hiddenColumns": []
        },
        "graphChartSettings": {
          "connectNulls": false
        },
        "honeycombSettings": {
          "showHive": true,
          "showLegend": true,
          "showLabels": false
        }
      },
      "queriesSettings": {
        "resolution": ""
      },
      "metricExpressions": [
        "resolution=Inf&((redis.redis_allocator_allocated:splitBy():sort(value(auto,descending)):limit(20)/redis.bdb_memory_limit:splitBy():sort(value(auto,descending)):limit(20))*100):limit(100):names",
        "resolution=null&((redis.redis_allocator_allocated:splitBy():sort(value(auto,descending)):limit(20)/redis.bdb_memory_limit:splitBy():sort(value(auto,descending)):limit(20))*100)"
      ]
    },
    {
      "name": "Resident Memory",
      "tileType": "DATA_EXPLORER",
      "configured": true,
      "bounds": {
        "top": 304,
        "left": 380,
        "width": 418,
        "height": 228
      },
      "tileFilter": {},
      "isAutoRefreshDisabled": false,
      "customName": "Data explorer results",
      "queries": [
        {
          "id": "A",
          "spaceAggregation": "AUTO",
          "timeAggregation": "DEFAULT",
          "splitBy": [],
          "metricSelector": "redis.redis_process_resident_memory_bytes:splitBy():sort(value(auto,descending)):limit(20)",
          "rate": "NONE",
          "enabled": true
        }
      ],
      "visualConfig": {
        "type": "GRAPH_CHART",
        "global": {},
        "rules": [
          {
            "matcher": "A:",
            "properties": {
              "color": "DEFAULT"
            },
            "seriesOverrides": []
          }
        ],
        "axes": {
          "xAxis": {
            "displayName": "",
            "visible": true
          },
          "yAxes": [
            {
              "displayName": "",
              "visible": true,
              "min": "AUTO",
              "max": "AUTO",
              "position": "LEFT",
              "queryIds": [
                "A"
              ],
              "defaultAxis": true
            }
          ]
        },
        "heatmapSettings": {
          "yAxis": "VALUE",
          "showLabels": false
        },
        "singleValueSettings": {
          "showTrend": true,
          "showSparkLine": true,
          "linkTileColorToThreshold": true
        },
        "thresholds": [
          {
            "axisTarget": "LEFT",
            "rules": [
              {
                "color": "#7dc540"
              },
              {
                "color": "#f5d30f"
              },
              {
                "color": "#dc172a"
              }
            ],
            "visible": true
          }
        ],
        "tableSettings": {
          "hiddenColumns": []
        },
        "graphChartSettings": {
          "connectNulls": false
        },
        "honeycombSettings": {
          "showHive": true,
          "showLegend": true,
          "showLabels": false
        }
      },
      "queriesSettings": {
        "resolution": ""
      },
      "metricExpressions": [
        "resolution=null&(redis.redis_process_resident_memory_bytes:splitBy():sort(value(auto,descending)):limit(20)):limit(100):names"
      ]
    },
    {
      "name": "Virtual Memory",
      "tileType": "DATA_EXPLORER",
      "configured": true,
      "bounds": {
        "top": 304,
        "left": 798,
        "width": 380,
        "height": 228
      },
      "tileFilter": {},
      "isAutoRefreshDisabled": false,
      "customName": "Data explorer results",
      "queries": [
        {
          "id": "A",
          "spaceAggregation": "AUTO",
          "timeAggregation": "DEFAULT",
          "splitBy": [],
          "metricSelector": "redis.redis_process_resident_memory_bytes:splitBy():sort(value(auto,descending)):limit(20)",
          "rate": "NONE",
          "enabled": true
        }
      ],
      "visualConfig": {
        "type": "GRAPH_CHART",
        "global": {},
        "rules": [
          {
            "matcher": "A:",
            "properties": {
              "color": "DEFAULT"
            },
            "seriesOverrides": []
          }
        ],
        "axes": {
          "xAxis": {
            "displayName": "",
            "visible": true
          },
          "yAxes": [
            {
              "displayName": "",
              "visible": true,
              "min": "AUTO",
              "max": "AUTO",
              "position": "LEFT",
              "queryIds": [
                "A"
              ],
              "defaultAxis": true
            }
          ]
        },
        "heatmapSettings": {
          "yAxis": "VALUE"
        },
        "thresholds": [
          {
            "axisTarget": "LEFT",
            "rules": [
              {
                "color": "#7dc540"
              },
              {
                "color": "#f5d30f"
              },
              {
                "color": "#dc172a"
              }
            ],
            "visible": true
          }
        ],
        "tableSettings": {
          "hiddenColumns": []
        },
        "graphChartSettings": {
          "connectNulls": false
        },
        "honeycombSettings": {
          "showHive": true,
          "showLegend": true,
          "showLabels": false
        }
      },
      "queriesSettings": {
        "resolution": ""
      },
      "metricExpressions": [
        "resolution=null&(redis.redis_process_resident_memory_bytes:splitBy():sort(value(auto,descending)):limit(20)):limit(100):names"
      ]
    },
    {
      "name": "Fragmentation",
      "tileType": "DATA_EXPLORER",
      "configured": true,
      "bounds": {
        "top": 304,
        "left": 1178,
        "width": 418,
        "height": 228
      },
      "tileFilter": {},
      "isAutoRefreshDisabled": false,
      "customName": "Data explorer results",
      "queries": [
        {
          "id": "A",
          "spaceAggregation": "AUTO",
          "timeAggregation": "DEFAULT",
          "splitBy": [],
          "metricSelector": "redis.redis_mem_replication_backlog:splitBy():sort(value(auto,descending)):limit(20)",
          "rate": "NONE",
          "enabled": true
        }
      ],
      "visualConfig": {
        "type": "GRAPH_CHART",
        "global": {},
        "rules": [
          {
            "matcher": "A:",
            "properties": {
              "color": "DEFAULT"
            },
            "seriesOverrides": []
          }
        ],
        "axes": {
          "xAxis": {
            "displayName": "",
            "visible": true
          },
          "yAxes": [
            {
              "displayName": "",
              "visible": true,
              "min": "AUTO",
              "max": "AUTO",
              "position": "LEFT",
              "queryIds": [
                "A"
              ],
              "defaultAxis": true
            }
          ]
        },
        "heatmapSettings": {
          "yAxis": "VALUE"
        },
        "thresholds": [
          {
            "axisTarget": "LEFT",
            "rules": [
              {
                "color": "#7dc540"
              },
              {
                "color": "#f5d30f"
              },
              {
                "color": "#dc172a"
              }
            ],
            "visible": true
          }
        ],
        "tableSettings": {
          "hiddenColumns": []
        },
        "graphChartSettings": {
          "connectNulls": false
        },
        "honeycombSettings": {
          "showHive": true,
          "showLegend": true,
          "showLabels": false
        }
      },
      "queriesSettings": {
        "resolution": ""
      },
      "metricExpressions": [
        "resolution=null&(redis.redis_mem_replication_backlog:splitBy():sort(value(auto,descending)):limit(20)):limit(100):names"
      ]
    },
    {
      "name": "Process CPU",
      "tileType": "DATA_EXPLORER",
      "configured": true,
      "bounds": {
        "top": 570,
        "left": 0,
        "width": 532,
        "height": 228
      },
      "tileFilter": {},
      "isAutoRefreshDisabled": false,
      "customName": "Data explorer results",
      "queries": [
        {
          "id": "A",
          "spaceAggregation": "AUTO",
          "timeAggregation": "DEFAULT",
          "splitBy": [],
          "metricSelector": "redis.redis_process_cpu_user_seconds_total:splitBy():sort(value(auto,descending)):limit(20)",
          "rate": "NONE",
          "enabled": true
        },
        {
          "id": "B",
          "spaceAggregation": "AUTO",
          "timeAggregation": "DEFAULT",
          "splitBy": [],
          "metricSelector": "redis.redis_process_cpu_user_seconds_total:splitBy():sort(value(auto,descending)):limit(20)",
          "rate": "NONE",
          "enabled": true
        }
      ],
      "visualConfig": {
        "type": "GRAPH_CHART",
        "global": {},
        "rules": [
          {
            "matcher": "A:",
            "properties": {
              "color": "DEFAULT"
            },
            "seriesOverrides": []
          },
          {
            "matcher": "B:",
            "properties": {
              "color": "DEFAULT"
            },
            "seriesOverrides": []
          }
        ],
        "axes": {
          "xAxis": {
            "displayName": "",
            "visible": true
          },
          "yAxes": [
            {
              "displayName": "",
              "visible": true,
              "min": "AUTO",
              "max": "AUTO",
              "position": "LEFT",
              "queryIds": [
                "A",
                "B"
              ],
              "defaultAxis": true
            }
          ]
        },
        "heatmapSettings": {
          "yAxis": "VALUE",
          "showLabels": false
        },
        "singleValueSettings": {
          "showTrend": true,
          "showSparkLine": true,
          "linkTileColorToThreshold": true
        },
        "thresholds": [
          {
            "axisTarget": "LEFT",
            "rules": [
              {
                "color": "#7dc540"
              },
              {
                "color": "#f5d30f"
              },
              {
                "color": "#dc172a"
              }
            ],
            "visible": true
          }
        ],
        "tableSettings": {
          "hiddenColumns": []
        },
        "graphChartSettings": {
          "connectNulls": false
        },
        "honeycombSettings": {
          "showHive": true,
          "showLegend": true,
          "showLabels": false
        }
      },
      "queriesSettings": {
        "resolution": ""
      },
      "metricExpressions": [
        "resolution=null&(redis.redis_process_cpu_user_seconds_total:splitBy():sort(value(auto,descending)):limit(20)):limit(100):names,(redis.redis_process_cpu_user_seconds_total:splitBy():sort(value(auto,descending)):limit(20)):limit(100):names"
      ]
    },
    {
      "name": "Main Thread",
      "tileType": "DATA_EXPLORER",
      "configured": true,
      "bounds": {
        "top": 570,
        "left": 1064,
        "width": 532,
        "height": 228
      },
      "tileFilter": {},
      "isAutoRefreshDisabled": false,
      "customName": "Data explorer results",
      "queries": [
        {
          "id": "A",
          "spaceAggregation": "AUTO",
          "timeAggregation": "DEFAULT",
          "splitBy": [],
          "metricSelector": "redis.redis_process_main_thread_cpu_system_seconds_total:splitBy():sort(value(auto,descending)):limit(20)",
          "rate": "NONE",
          "enabled": true
        },
        {
          "id": "B",
          "spaceAggregation": "AUTO",
          "timeAggregation": "DEFAULT",
          "splitBy": [],
          "metricSelector": "redis.redis_process_main_thread_cpu_user_seconds_total:splitBy():sort(value(auto,descending)):limit(20)",
          "rate": "NONE",
          "enabled": true
        }
      ],
      "visualConfig": {
        "type": "GRAPH_CHART",
        "global": {},
        "rules": [
          {
            "matcher": "A:",
            "properties": {
              "color": "DEFAULT"
            },
            "seriesOverrides": []
          },
          {
            "matcher": "B:",
            "properties": {
              "color": "DEFAULT"
            },
            "seriesOverrides": []
          }
        ],
        "axes": {
          "xAxis": {
            "displayName": "",
            "visible": true
          },
          "yAxes": [
            {
              "displayName": "",
              "visible": true,
              "min": "AUTO",
              "max": "AUTO",
              "position": "LEFT",
              "queryIds": [
                "A",
                "B"
              ],
              "defaultAxis": true
            }
          ]
        },
        "heatmapSettings": {
          "yAxis": "VALUE"
        },
        "thresholds": [
          {
            "axisTarget": "LEFT",
            "rules": [
              {
                "color": "#7dc540"
              },
              {
                "color": "#f5d30f"
              },
              {
                "color": "#dc172a"
              }
            ],
            "visible": true
          }
        ],
        "tableSettings": {
          "hiddenColumns": []
        },
        "graphChartSettings": {
          "connectNulls": false
        },
        "honeycombSettings": {
          "showHive": true,
          "showLegend": true,
          "showLabels": false
        }
      },
      "queriesSettings": {
        "resolution": ""
      },
      "metricExpressions": [
        "resolution=null&(redis.redis_process_main_thread_cpu_system_seconds_total:splitBy():sort(value(auto,descending)):limit(20)):limit(100):names,(redis.redis_process_main_thread_cpu_user_seconds_total:splitBy():sort(value(auto,descending)):limit(20)):limit(100):names"
      ]
    },
    {
      "name": "CPU Usage",
      "tileType": "DATA_EXPLORER",
      "configured": true,
      "bounds": {
        "top": 570,
        "left": 532,
        "width": 532,
        "height": 228
      },
      "tileFilter": {},
      "isAutoRefreshDisabled": false,
      "customName": "Data explorer results",
      "queries": [
        {
          "id": "A",
          "spaceAggregation": "AUTO",
          "timeAggregation": "DEFAULT",
          "splitBy": [],
          "metricSelector": "redis.redis_process_cpu_usage_percent:splitBy():sort(value(auto,descending)):limit(20)",
          "rate": "NONE",
          "enabled": true
        }
      ],
      "visualConfig": {
        "type": "GRAPH_CHART",
        "global": {},
        "rules": [
          {
            "matcher": "A:",
            "properties": {
              "color": "DEFAULT"
            },
            "seriesOverrides": []
          }
        ],
        "axes": {
          "xAxis": {
            "displayName": "",
            "visible": true
          },
          "yAxes": [
            {
              "displayName": "",
              "visible": true,
              "min": "AUTO",
              "max": "AUTO",
              "position": "LEFT",
              "queryIds": [
                "A"
              ],
              "defaultAxis": true
            }
          ]
        },
        "heatmapSettings": {
          "yAxis": "VALUE"
        },
        "thresholds": [
          {
            "axisTarget": "LEFT",
            "rules": [
              {
                "color": "#7dc540"
              },
              {
                "color": "#f5d30f"
              },
              {
                "color": "#dc172a"
              }
            ],
            "visible": true
          }
        ],
        "tableSettings": {
          "hiddenColumns": []
        },
        "graphChartSettings": {
          "connectNulls": false
        },
        "honeycombSettings": {
          "showHive": true,
          "showLegend": true,
          "showLabels": false
        }
      },
      "queriesSettings": {
        "resolution": ""
      },
      "metricExpressions": [
        "resolution=null&(redis.redis_process_cpu_usage_percent:splitBy():sort(value(auto,descending)):limit(20)):limit(100):names"
      ]
    },
    {
      "name": "Incoming/OutgoingTraffic",
      "tileType": "DATA_EXPLORER",
      "configured": true,
      "bounds": {
        "top": 836,
        "left": 1064,
        "width": 532,
        "height": 228
      },
      "tileFilter": {},
      "isAutoRefreshDisabled": false,
      "customName": "Data explorer results",
      "queries": [
        {
          "id": "A",
          "metric": "redis.bdb_ingress_bytes",
          "spaceAggregation": "AUTO",
          "timeAggregation": "DEFAULT",
          "splitBy": [],
          "sortBy": "DESC",
          "sortByDimension": "",
          "filterBy": {
            "nestedFilters": [],
            "criteria": []
          },
          "limit": 20,
          "rate": "NONE",
          "enabled": true
        },
        {
          "id": "B",
          "spaceAggregation": "AUTO",
          "timeAggregation": "DEFAULT",
          "splitBy": [],
          "metricSelector": "redis.bdb_egress_bytes:splitBy():sort(value(auto,descending)):limit(20)",
          "rate": "NONE",
          "enabled": true
        }
      ],
      "visualConfig": {
        "type": "GRAPH_CHART",
        "global": {},
        "rules": [
          {
            "matcher": "A:",
            "properties": {
              "color": "DEFAULT"
            },
            "seriesOverrides": []
          },
          {
            "matcher": "B:",
            "properties": {
              "color": "DEFAULT"
            },
            "seriesOverrides": []
          }
        ],
        "axes": {
          "xAxis": {
            "displayName": "",
            "visible": true
          },
          "yAxes": [
            {
              "displayName": "",
              "visible": true,
              "min": "AUTO",
              "max": "AUTO",
              "position": "LEFT",
              "queryIds": [
                "A",
                "B"
              ],
              "defaultAxis": true
            }
          ]
        },
        "heatmapSettings": {
          "yAxis": "VALUE",
          "showLabels": false
        },
        "singleValueSettings": {
          "showTrend": true,
          "showSparkLine": true,
          "linkTileColorToThreshold": true
        },
        "thresholds": [
          {
            "axisTarget": "LEFT",
            "rules": [
              {
                "color": "#7dc540"
              },
              {
                "color": "#f5d30f"
              },
              {
                "color": "#dc172a"
              }
            ],
            "visible": true
          }
        ],
        "tableSettings": {
          "hiddenColumns": []
        },
        "graphChartSettings": {
          "connectNulls": false
        },
        "honeycombSettings": {
          "showHive": true,
          "showLegend": true,
          "showLabels": false
        }
      },
      "queriesSettings": {
        "resolution": ""
      },
      "metricExpressions": [
        "resolution=null&(redis.bdb_ingress_bytes:splitBy():sort(value(auto,descending)):limit(20)):limit(100):names,(redis.bdb_egress_bytes:splitBy():sort(value(auto,descending)):limit(20)):limit(100):names"
      ]
    },
    {
      "name": "Current Connections",
      "tileType": "DATA_EXPLORER",
      "configured": true,
      "bounds": {
        "top": 836,
        "left": 532,
        "width": 532,
        "height": 228
      },
      "tileFilter": {},
      "isAutoRefreshDisabled": false,
      "customName": "Data explorer results",
      "queries": [
        {
          "id": "C",
          "spaceAggregation": "AUTO",
          "timeAggregation": "DEFAULT",
          "splitBy": [],
          "metricSelector": "redis.redis_connected_clients:splitBy():sort(value(auto,descending)):limit(20)",
          "rate": "NONE",
          "enabled": true
        },
        {
          "id": "D",
          "spaceAggregation": "AUTO",
          "timeAggregation": "DEFAULT",
          "splitBy": [],
          "metricSelector": "redis.redis_blocked_clients:splitBy():sort(value(auto,descending)):limit(20)",
          "rate": "NONE",
          "enabled": true
        }
      ],
      "visualConfig": {
        "type": "GRAPH_CHART",
        "global": {},
        "rules": [
          {
            "matcher": "C:",
            "properties": {
              "color": "DEFAULT"
            },
            "seriesOverrides": []
          },
          {
            "matcher": "D:",
            "properties": {
              "color": "DEFAULT"
            },
            "seriesOverrides": []
          }
        ],
        "axes": {
          "xAxis": {
            "displayName": "",
            "visible": true
          },
          "yAxes": [
            {
              "displayName": "",
              "visible": true,
              "min": "AUTO",
              "max": "AUTO",
              "position": "LEFT",
              "queryIds": [
                "C",
                "D"
              ],
              "defaultAxis": true
            },
            {
              "displayName": "",
              "visible": true,
              "min": "AUTO",
              "max": "AUTO",
              "position": "RIGHT",
              "queryIds": [
                "E"
              ],
              "defaultAxis": true
            }
          ]
        },
        "heatmapSettings": {
          "yAxis": "VALUE",
          "showLabels": false
        },
        "singleValueSettings": {
          "showTrend": true,
          "showSparkLine": true,
          "linkTileColorToThreshold": true
        },
        "thresholds": [
          {
            "axisTarget": "LEFT",
            "rules": [
              {
                "color": "#7dc540"
              },
              {
                "color": "#f5d30f"
              },
              {
                "color": "#dc172a"
              }
            ],
            "visible": true
          }
        ],
        "tableSettings": {
          "hiddenColumns": []
        },
        "graphChartSettings": {
          "connectNulls": false
        },
        "honeycombSettings": {
          "showHive": true,
          "showLegend": true,
          "showLabels": false
        }
      },
      "queriesSettings": {
        "resolution": ""
      },
      "metricExpressions": [
        "resolution=null&(redis.redis_connected_clients:splitBy():sort(value(auto,descending)):limit(20)):limit(100):names,(redis.redis_blocked_clients:splitBy():sort(value(auto,descending)):limit(20)):limit(100):names"
      ]
    },
    {
      "name": "Shard Allocation Fragmentation (#)",
      "tileType": "DATA_EXPLORER",
      "configured": true,
      "bounds": {
        "top": 1368,
        "left": 798,
        "width": 380,
        "height": 228
      },
      "tileFilter": {},
      "isAutoRefreshDisabled": false
    },
    {
      "name": "Expired Keys",
      "tileType": "DATA_EXPLORER",
      "configured": true,
      "bounds": {
        "top": 1102,
        "left": 1178,
        "width": 418,
        "height": 228
      },
      "tileFilter": {},
      "isAutoRefreshDisabled": false,
      "customName": "Data explorer results",
      "queries": [
        {
          "id": "A",
          "spaceAggregation": "AUTO",
          "timeAggregation": "DEFAULT",
          "splitBy": [
            "activation_endpoint",
            "bdb",
            "cluster",
            "dt.entity.gcp_zone",
            "dt.entity.host",
            "dt.entity.prometheus:com_dynatrace_extension_redis_cluster",
            "dt.entity.prometheus:com_dynatrace_extension_redis_database",
            "dt.entity.prometheus:com_dynatrace_extension_redis_node",
            "dt.metrics.source",
            "gcp.instance.id",
            "gcp.project.id",
            "gcp.region",
            "gcp.zone",
            "host.name",
            "node",
            "redis",
            "role",
            "slots",
            "status"
          ],
          "metricSelector": "redis.redis_expired_keys",
          "rate": "NONE",
          "enabled": true
        }
      ],
      "visualConfig": {
        "type": "GRAPH_CHART",
        "global": {},
        "rules": [
          {
            "matcher": "A:",
            "properties": {
              "color": "DEFAULT"
            },
            "seriesOverrides": []
          }
        ],
        "axes": {
          "xAxis": {
            "displayName": "",
            "visible": true
          },
          "yAxes": [
            {
              "displayName": "",
              "visible": true,
              "min": "AUTO",
              "max": "AUTO",
              "position": "LEFT",
              "queryIds": [
                "A"
              ],
              "defaultAxis": true
            }
          ]
        },
        "heatmapSettings": {
          "yAxis": "VALUE"
        },
        "thresholds": [
          {
            "axisTarget": "LEFT",
            "rules": [
              {
                "color": "#7dc540"
              },
              {
                "color": "#f5d30f"
              },
              {
                "color": "#dc172a"
              }
            ],
            "visible": true
          }
        ],
        "tableSettings": {
          "hiddenColumns": []
        },
        "graphChartSettings": {
          "connectNulls": false
        },
        "honeycombSettings": {
          "showHive": true,
          "showLegend": true,
          "showLabels": false
        }
      },
      "queriesSettings": {
        "resolution": ""
      },
      "metricExpressions": [
        "resolution=null&(redis.redis_expired_keys):limit(100):names"
      ]
    },
    {
      "name": "Evicted Keys",
      "tileType": "DATA_EXPLORER",
      "configured": true,
      "bounds": {
        "top": 1102,
        "left": 798,
        "width": 380,
        "height": 228
      },
      "tileFilter": {},
      "isAutoRefreshDisabled": false,
      "customName": "Data explorer results",
      "queries": [
        {
          "id": "A",
          "spaceAggregation": "AUTO",
          "timeAggregation": "DEFAULT",
          "splitBy": [
            "activation_endpoint",
            "bdb",
            "cluster",
            "dt.entity.gcp_zone",
            "dt.entity.host",
            "dt.entity.prometheus:com_dynatrace_extension_redis_cluster",
            "dt.entity.prometheus:com_dynatrace_extension_redis_database",
            "dt.entity.prometheus:com_dynatrace_extension_redis_node",
            "dt.metrics.source",
            "gcp.instance.id",
            "gcp.project.id",
            "gcp.region",
            "gcp.zone",
            "host.name",
            "node",
            "redis",
            "role",
            "slots",
            "status"
          ],
          "metricSelector": "redis.redis_evicted_keys",
          "rate": "NONE",
          "enabled": true
        }
      ],
      "visualConfig": {
        "type": "GRAPH_CHART",
        "global": {},
        "rules": [
          {
            "matcher": "A:",
            "properties": {
              "color": "DEFAULT"
            },
            "seriesOverrides": []
          }
        ],
        "axes": {
          "xAxis": {
            "displayName": "",
            "visible": true
          },
          "yAxes": [
            {
              "displayName": "",
              "visible": true,
              "min": "AUTO",
              "max": "AUTO",
              "position": "LEFT",
              "queryIds": [
                "A"
              ],
              "defaultAxis": true
            }
          ]
        },
        "heatmapSettings": {
          "yAxis": "VALUE"
        },
        "thresholds": [
          {
            "axisTarget": "LEFT",
            "rules": [
              {
                "color": "#7dc540"
              },
              {
                "color": "#f5d30f"
              },
              {
                "color": "#dc172a"
              }
            ],
            "visible": true
          }
        ],
        "tableSettings": {
          "hiddenColumns": []
        },
        "graphChartSettings": {
          "connectNulls": false
        },
        "honeycombSettings": {
          "showHive": true,
          "showLegend": true,
          "showLabels": false
        }
      },
      "queriesSettings": {
        "resolution": ""
      },
      "metricExpressions": [
        "resolution=null&(redis.redis_evicted_keys):limit(100):names"
      ]
    },
    {
      "name": "Current Keys",
      "tileType": "DATA_EXPLORER",
      "configured": true,
      "bounds": {
        "top": 1102,
        "left": 418,
        "width": 380,
        "height": 228
      },
      "tileFilter": {},
      "isAutoRefreshDisabled": false,
      "customName": "Data explorer results",
      "queries": [
        {
          "id": "A",
          "spaceAggregation": "AUTO",
          "timeAggregation": "DEFAULT",
          "splitBy": [],
          "metricSelector": "redis.redis_db0_keys",
          "rate": "NONE",
          "enabled": true
        }
      ],
      "visualConfig": {
        "type": "GRAPH_CHART",
        "global": {},
        "rules": [
          {
            "matcher": "A:",
            "properties": {
              "color": "DEFAULT"
            },
            "seriesOverrides": []
          }
        ],
        "axes": {
          "xAxis": {
            "displayName": "",
            "visible": true
          },
          "yAxes": [
            {
              "displayName": "",
              "visible": true,
              "min": "AUTO",
              "max": "AUTO",
              "position": "LEFT",
              "queryIds": [
                "A"
              ],
              "defaultAxis": true
            }
          ]
        },
        "heatmapSettings": {
          "yAxis": "VALUE"
        },
        "thresholds": [
          {
            "axisTarget": "LEFT",
            "rules": [
              {
                "color": "#7dc540"
              },
              {
                "color": "#f5d30f"
              },
              {
                "color": "#dc172a"
              }
            ],
            "visible": true
          }
        ],
        "tableSettings": {
          "hiddenColumns": []
        },
        "graphChartSettings": {
          "connectNulls": false
        },
        "honeycombSettings": {
          "showHive": true,
          "showLegend": true,
          "showLabels": false
        }
      },
      "queriesSettings": {
        "resolution": ""
      },
      "metricExpressions": [
        "resolution=null&(redis.redis_db0_keys):limit(100):names"
      ]
    },
    {
      "name": "Shard Allocation Fragmentation (%)",
      "tileType": "DATA_EXPLORER",
      "configured": true,
      "bounds": {
        "top": 1368,
        "left": 1178,
        "width": 418,
        "height": 228
      },
      "tileFilter": {},
      "isAutoRefreshDisabled": false,
      "customName": "Data explorer results",
      "queries": [
        {
          "id": "A",
          "spaceAggregation": "AUTO",
          "timeAggregation": "DEFAULT",
          "splitBy": [
            "activation_endpoint",
            "bdb",
            "cluster",
            "dt.entity.gcp_zone",
            "dt.entity.host",
            "dt.entity.prometheus:com_dynatrace_extension_redis_cluster",
            "dt.entity.prometheus:com_dynatrace_extension_redis_database",
            "dt.entity.prometheus:com_dynatrace_extension_redis_node",
            "dt.metrics.source",
            "gcp.instance.id",
            "gcp.project.id",
            "gcp.region",
            "gcp.zone",
            "host.name",
            "node",
            "redis",
            "role",
            "slots",
            "status"
          ],
          "metricSelector": "redis.redis_allocator_active / redis.redis_allocator_allocated",
          "rate": "NONE",
          "enabled": true
        }
      ],
      "visualConfig": {
        "type": "GRAPH_CHART",
        "global": {},
        "rules": [
          {
            "matcher": "A:",
            "properties": {
              "color": "DEFAULT"
            },
            "seriesOverrides": []
          }
        ],
        "axes": {
          "xAxis": {
            "displayName": "",
            "visible": true
          },
          "yAxes": [
            {
              "displayName": "",
              "visible": true,
              "min": "AUTO",
              "max": "AUTO",
              "position": "LEFT",
              "queryIds": [
                "A"
              ],
              "defaultAxis": true
            }
          ]
        },
        "heatmapSettings": {
          "yAxis": "VALUE"
        },
        "thresholds": [
          {
            "axisTarget": "LEFT",
            "rules": [
              {
                "color": "#7dc540"
              },
              {
                "color": "#f5d30f"
              },
              {
                "color": "#dc172a"
              }
            ],
            "visible": true
          }
        ],
        "tableSettings": {
          "hiddenColumns": []
        },
        "graphChartSettings": {
          "connectNulls": false
        },
        "honeycombSettings": {
          "showHive": true,
          "showLegend": true,
          "showLabels": false
        }
      },
      "queriesSettings": {
        "resolution": ""
      },
      "metricExpressions": [
        "resolution=null&(redis.redis_allocator_active/redis.redis_allocator_allocated):limit(100):names"
      ]
    },
    {
      "name": "Total Keys",
      "tileType": "DATA_EXPLORER",
      "configured": true,
      "bounds": {
        "top": 1102,
        "left": 0,
        "width": 418,
        "height": 228
      },
      "tileFilter": {},
      "isAutoRefreshDisabled": false,
      "customName": "Single value",
      "queries": [
        {
          "id": "A",
          "spaceAggregation": "AUTO",
          "timeAggregation": "DEFAULT",
          "splitBy": [],
          "metricSelector": "redis.redis_db0_keys:splitBy():sort(value(auto,descending)):limit(20) + redis.redis_db0_expires:splitBy():sort(value(auto,descending)):limit(20)",
          "rate": "NONE",
          "enabled": true
        }
      ],
      "visualConfig": {
        "type": "GRAPH_CHART",
        "global": {},
        "rules": [
          {
            "matcher": "A:",
            "unitTransform": "auto",
            "valueFormat": "auto",
            "properties": {
              "color": "DEFAULT",
              "seriesType": "LINE"
            },
            "seriesOverrides": []
          }
        ],
        "axes": {
          "xAxis": {
            "displayName": "",
            "visible": true
          },
          "yAxes": [
            {
              "displayName": "",
              "visible": true,
              "min": "AUTO",
              "max": "AUTO",
              "position": "LEFT",
              "queryIds": [
                "B"
              ],
              "defaultAxis": true
            },
            {
              "displayName": "",
              "visible": true,
              "min": "AUTO",
              "max": "AUTO",
              "position": "LEFT",
              "queryIds": [
                "A"
              ],
              "defaultAxis": true
            }
          ]
        },
        "heatmapSettings": {
          "yAxis": "VALUE"
        },
        "singleValueSettings": {
          "showTrend": true,
          "showSparkLine": true,
          "linkTileColorToThreshold": true
        },
        "thresholds": [
          {
            "axisTarget": "LEFT",
            "rules": [
              {
                "color": "#7dc540"
              },
              {
                "color": "#f5d30f"
              },
              {
                "color": "#dc172a"
              }
            ],
            "visible": true
          }
        ],
        "tableSettings": {
          "hiddenColumns": []
        },
        "graphChartSettings": {
          "connectNulls": false
        },
        "honeycombSettings": {
          "showHive": true,
          "showLegend": true,
          "showLabels": false
        }
      },
      "queriesSettings": {
        "resolution": ""
      },
      "metricExpressions": [
        "resolution=null&(redis.redis_db0_keys:splitBy():sort(value(auto,descending)):limit(20)+redis.redis_db0_expires:splitBy():sort(value(auto,descending)):limit(20)):limit(100):names"
      ]
    },
    {
      "name": "Status",
      "tileType": "DATA_EXPLORER",
      "configured": true,
      "bounds": {
        "top": 38,
        "left": 0,
        "width": 266,
        "height": 228
      },
      "tileFilter": {},
      "isAutoRefreshDisabled": false,
      "customName": "Single value",
      "queries": [
        {
          "id": "A",
          "metric": "redis.redis_up",
          "spaceAggregation": "AUTO",
          "timeAggregation": "DEFAULT",
          "splitBy": [
            "cluster",
            "node",
            "redis"
          ],
          "sortBy": "DESC",
          "sortByDimension": "",
          "filterBy": {
            "nestedFilters": [],
            "criteria": []
          },
          "limit": 20,
          "rate": "NONE",
          "enabled": true
        }
      ],
      "visualConfig": {
        "type": "TABLE",
        "global": {},
        "rules": [
          {
            "matcher": "A:",
            "properties": {
              "color": "DEFAULT"
            },
            "seriesOverrides": []
          }
        ],
        "axes": {
          "xAxis": {
            "visible": true
          },
          "yAxes": []
        },
        "heatmapSettings": {
          "yAxis": "VALUE"
        },
        "singleValueSettings": {
          "showTrend": true,
          "showSparkLine": false,
          "linkTileColorToThreshold": true
        },
        "thresholds": [
          {
            "axisTarget": "LEFT",
            "columnId": "Redis Up Status",
            "rules": [
              {
                "value": 0,
                "color": "#7dc540"
              },
              {
                "value": -1,
                "color": "#f5d30f"
              },
              {
                "value": -1,
                "color": "#dc172a"
              }
            ],
            "queryId": "A",
            "visible": true
          }
        ],
        "tableSettings": {
          "hiddenColumns": [
            "A:dt.entity.prometheus:com_dynatrace_extension_redis_cluster.name",
            "A:dt.entity.prometheus:com_dynatrace_extension_redis_node.name",
            "A:redis.name",
            "A:cluster.name",
            "A:bdb.name",
            "A:node.name"
          ]
        },
        "graphChartSettings": {
          "connectNulls": false
        },
        "honeycombSettings": {
          "showHive": true,
          "showLegend": true,
          "showLabels": false
        }
      },
      "queriesSettings": {
        "resolution": ""
      },
      "metricExpressions": [
        "resolution=Inf&(redis.redis_up:splitBy(cluster,node,redis):sort(value(auto,descending)):limit(20)):names"
      ]
    }
  ]
}
